vtc_scrypt_new.cp35-win_amd64.pyd
vtc_scrypt_new-1.1.5.dist-info/METADATA
vtc_scrypt_new-1.1.5.dist-info/RECORD
vtc_scrypt_new-1.1.5.dist-info/WHEEL
vtc_scrypt_new-1.1.5.dist-info/top_level.txt
