Metadata-Version: 2.1
Name: vtc-scrypt-new
Version: 1.1.5
Summary: Bindings for scrypt-n proof of work used by Vertcoin
Home-page: UNKNOWN
Author: UNKNOWN
Author-email: UNKNOWN
License: UNKNOWN
Platform: UNKNOWN
